{
    "CurrencyIsoCode": "USD",
    "IsActive": true,
    "IsLocked": false,
    "IsOmniScriptEmbeddable": false,
    "MayEdit": true,
    "Name": "FundingOpportunitySearch",
    "OmniProcessId": {
        "Name": "GrantIntakeAnalyzeProject",
        "VlocityDataPackType": "VlocityMatchingKeyObject",
        "VlocityMatchingRecordSourceKey": "OmniProcess/GrantIntake/AnalyzeProjectV3/English",
        "VlocityRecordSObjectType": "OmniProcess"
    },
    "PropertySetConfig": {
        "actionMessage": "",
        "bundle": "DRFundingList",
        "chainOnStep": false,
        "disOnTplt": false,
        "executionConditionalFormula": "",
        "failOnStepError": true,
        "failureConditionalFormula": "",
        "failureResponse": {
        },
        "ignoreCache": true,
        "isActive": true,
        "responseJSONNode": "fundingSearch",
        "responseJSONPath": "",
        "sendJSONNode": "",
        "sendJSONPath": "",
        "useFormulas": true
    },
    "Type": "DataRaptor Extract Action",
    "VlocityDataPackType": "SObject",
    "VlocityRecordSObjectType": "OmniProcessElement",
    "VlocityRecordSourceKey": "OmniProcessElement/OmniProcess/GrantIntake/AnalyzeProjectV3/English/FundingOpportunitySearch"
}